roundrobin_match/__init__.py
roundrobin_match/cli.py
roundrobin_match/main.py
roundrobin_match/version.py
roundrobin_match-0.1.1.dist-info/LICENSE
roundrobin_match-0.1.1.dist-info/METADATA
roundrobin_match-0.1.1.dist-info/WHEEL
roundrobin_match-0.1.1.dist-info/entry_points.txt
roundrobin_match-0.1.1.dist-info/top_level.txt
roundrobin_match-0.1.1.dist-info/RECORD
