Metadata-Version: 2.1
Name: roundrobin-match
Version: 0.1.1
Summary: A CLI library for creating 1on1 and game match schedules
Author-email: kyoto7250 <50972773+kyoto7250@users.noreply.github.com>
Maintainer-email: kyoto7250 <50972773+kyoto7250@users.noreply.github.com>
License: MIT License
Project-URL: Homepage, https://github.com/kyoto7250/roundrobin_match
Project-URL: Documentation, https://github.com/kyoto7250/roundrobin_match
Project-URL: Repository, https://github.com/kyoto7250/roundrobin_match
Project-URL: Issues, https://github.com/kyoto7250/roundrobin_match/issues
Keywords: algorithm,cli
Requires-Python: >=3.10
License-File: LICENSE
